cubetimer/__init__.py
cubetimer/__main__.py
cubetimer/_scrambler.py
cubetimer/_version.py
cubetimer/_version.pyi
cubetimer/app.py
cubetimer/main.py
cubetimer/py.typed
cubetimer-0.0.1.dist-info/METADATA
cubetimer-0.0.1.dist-info/WHEEL
cubetimer-0.0.1.dist-info/entry_points.txt
cubetimer-0.0.1.dist-info/licenses/LICENSE
cubetimer-0.0.1.dist-info/RECORD
