Metadata-Version: 2.4
Name: cubetimer
Version: 0.0.1
Summary: A Rubik's Cube timer for speedsolving/training with a terminal user interface.
Project-URL: Homepage, https://github.com/agriyakhetarpal/cubetimer
Project-URL: Bug Tracker, https://github.com/agriyakhetarpal/cubetimer/issues
Project-URL: Changelog, https://github.com/agriyakhetarpal/cubetimer/releases
Author-email: Agriya Khetarpal <agriyakhetarpal@outlook.com>
License-Expression: Apache-2.0
License-File: LICENSE
Keywords: cli,puzzle,rubiks-cube,speedcubing,speedsolving,terminal,textual,timer,timing,tui
Classifier: Development Status :: 2 - Pre-Alpha
Classifier: Environment :: Console
Classifier: Environment :: MacOS X
Classifier: Environment :: Win32 (MS Windows)
Classifier: Intended Audience :: End Users/Desktop
Classifier: License :: OSI Approved :: MIT License
Classifier: Operating System :: OS Independent
Classifier: Programming Language :: Python :: 3
Classifier: Programming Language :: Python :: 3.9
Classifier: Programming Language :: Python :: 3.10
Classifier: Programming Language :: Python :: 3.11
Classifier: Programming Language :: Python :: 3.12
Classifier: Programming Language :: Python :: 3.13
Classifier: Topic :: Games/Entertainment
Classifier: Topic :: Games/Entertainment :: Puzzle Games
Classifier: Topic :: System :: Monitoring
Classifier: Topic :: Terminals
Classifier: Topic :: Utilities
Classifier: Typing :: Typed
Requires-Python: >=3.9
Requires-Dist: platformdirs
Requires-Dist: textual==6.2.1
